soft_moe_pytorch/__init__.py
soft_moe_pytorch/distributed.py
soft_moe_pytorch/soft_moe.py
soft_moe_pytorch/soft_moe_with_dynamic_slots.py
soft_moe_pytorch-0.1.9.dist-info/licenses/LICENSE
soft_moe_pytorch-0.1.9.dist-info/METADATA
soft_moe_pytorch-0.1.9.dist-info/WHEEL
soft_moe_pytorch-0.1.9.dist-info/top_level.txt
soft_moe_pytorch-0.1.9.dist-info/RECORD
